nctalk.py
nctalk-0.0.4.dist-info/METADATA
nctalk-0.0.4.dist-info/WHEEL
nctalk-0.0.4.dist-info/entry_points.txt
nctalk-0.0.4.dist-info/top_level.txt
nctalk-0.0.4.dist-info/RECORD
